bsdploy/__init__.py
bsdploy/bootstrap_utils.py
bsdploy/download.py
bsdploy/enable_root_login_on_daemonology.sh
bsdploy/fabfile_daemonology.py
bsdploy/fabfile_digitalocean.py
bsdploy/fabfile_mfsbsd.py
bsdploy/fabutils.py
bsdploy/startup-ansible-jail.sh
bsdploy/bootstrap-files/FreeBSD.conf
bsdploy/bootstrap-files/daemonology-files.yml
bsdploy/bootstrap-files/files.yml
bsdploy/bootstrap-files/make.conf
bsdploy/bootstrap-files/pf.conf
bsdploy/bootstrap-files/pkg.conf
bsdploy/bootstrap-files/rc.conf
bsdploy/bootstrap-files/sshd_config
bsdploy/library/sysrc
bsdploy/library/zpool
bsdploy/roles/jailhost.yml
bsdploy/roles/bsdploy_clean_ansible_files/tasks/main.yml
bsdploy/roles/dhcp_host/defaults/main.yml
bsdploy/roles/dhcp_host/handlers/main.yml
bsdploy/roles/dhcp_host/tasks/main.yml
bsdploy/roles/dhcp_host/templates/dhclient-exit-hooks
bsdploy/roles/jails_host/defaults/main.yml
bsdploy/roles/jails_host/files/base_flavour_motd
bsdploy/roles/jails_host/files/base_flavour_rc.conf
bsdploy/roles/jails_host/files/base_flavour_sshd_config
bsdploy/roles/jails_host/files/make.conf
bsdploy/roles/jails_host/handlers/main.yml
bsdploy/roles/jails_host/tasks/main.yml
bsdploy/roles/jails_host/tasks/ntpd.yml
bsdploy/roles/jails_host/tasks/obsolete-ipf.yml
bsdploy/roles/jails_host/tasks/pf.yml
bsdploy/roles/jails_host/templates/FreeBSD.conf
bsdploy/roles/jails_host/templates/ezjail.conf
bsdploy/roles/jails_host/templates/pf.conf
bsdploy/roles/jails_host/templates/pkg.conf
bsdploy/roles/zfs_auto_snapshot/tasks/main.yml
bsdploy/roles/zfs_auto_snapshot/templates/010.zfs-snapshot
bsdploy/tests/__init__.py
bsdploy/tests/conftest.py
bsdploy/tests/packagesite.txz
bsdploy/tests/test_bootstrap_daemonology.py
bsdploy/tests/test_bootstrap_mfsbsd.py
bsdploy/tests/test_bootstrap_utils.py
bsdploy/tests/test_bsdploy.py
bsdploy/tests/test_quickstart.py
bsdploy/tests/test_roles.py
bsdploy/tests/test_templates.py
bsdploy-3.0.0.dist-info/LICENSE.txt
bsdploy-3.0.0.dist-info/METADATA
bsdploy-3.0.0.dist-info/WHEEL
bsdploy-3.0.0.dist-info/entry_points.txt
bsdploy-3.0.0.dist-info/top_level.txt
bsdploy-3.0.0.dist-info/RECORD
