Metadata-Version: 2.1
Name: bsdploy
Version: 3.0.0
Summary: A tool to remotely provision, configure and maintain FreeBSD jails
Home-page: http://github.com/ployground/bsdploy
Author: Tom Lazar
Author-email: tom@tomster.org
Maintainer: Florian Schulze
Maintainer-email: mail@florian-schulze.net
License: BSD 3-Clause License
Platform: UNKNOWN
Classifier: Development Status :: 4 - Beta
Classifier: Environment :: Console
Classifier: Intended Audience :: System Administrators
Classifier: Operating System :: POSIX :: BSD :: FreeBSD
Classifier: Programming Language :: Python :: 2.7
Classifier: Programming Language :: Python :: 3.7
Classifier: Programming Language :: Python :: 3.8
Classifier: Programming Language :: Python :: 3.9
Classifier: Programming Language :: Python :: 3.10
Classifier: Topic :: System :: Installation/Setup
Classifier: Topic :: System :: Systems Administration
Requires-Python: >=2.7, !=3.0.*, !=3.1.*, !=3.2.*, !=3.3.*, !=3.4.*, !=3.5.*, !=3.6.*
License-File: LICENSE.txt
Requires-Dist: backports.lzma
Requires-Dist: PyYAML
Requires-Dist: jinja2
Requires-Dist: setuptools
Requires-Dist: ploy (>=2.0.0)
Requires-Dist: ploy-ansible (>=2.0.0)
Requires-Dist: ploy-ezjail (>=2.0.0)
Requires-Dist: ploy-fabric (>=2.0.0)
Requires-Dist: ansible ; python_version >= "3.10"
Provides-Extra: development
Requires-Dist: Sphinx ; extra == 'development'
Requires-Dist: repoze.sphinx.autointerface ; extra == 'development'
Requires-Dist: coverage ; extra == 'development'
Requires-Dist: jarn.mkrelease ; extra == 'development'
Requires-Dist: ploy-virtualbox (>=2dev) ; extra == 'development'
Requires-Dist: pytest (>=2.4.2) ; extra == 'development'
Requires-Dist: pytest-flake8 ; extra == 'development'
Requires-Dist: tox ; extra == 'development'
Requires-Dist: mock ; extra == 'development'
